{
  "hash": "92b118fa9aa9e8b6299bc856d1d1f4b3",
  "result": {
    "engine": "knitr",
    "markdown": "---\ntitle: \"discovr_18 - Exploratory Factor Analysis\"\nauthor: \"Colin Madland\"\ndate: \"2024-02-27\"\ncategories: [efa, R, discovr]\neditor: visual\nimage: \"happy-rock.jpeg\"\nfreeze: auto\n---\n\n::: {.cell}\n\n```{.r .cell-code}\nlibrary(tidyverse)\n```\n\n::: {.cell-output .cell-output-stderr}\n\n```\n── Attaching core tidyverse packages ──────────────────────── tidyverse 2.0.0 ──\n✔ dplyr     1.1.4     ✔ readr     2.1.5\n✔ forcats   1.0.0     ✔ stringr   1.5.1\n✔ ggplot2   3.5.1     ✔ tibble    3.2.1\n✔ lubridate 1.9.3     ✔ tidyr     1.3.1\n✔ purrr     1.0.2     \n── Conflicts ────────────────────────────────────────── tidyverse_conflicts() ──\n✖ dplyr::filter() masks stats::filter()\n✖ dplyr::lag()    masks stats::lag()\nℹ Use the conflicted package (<http://conflicted.r-lib.org/>) to force all conflicts to become errors\n```\n\n\n:::\n\n```{.r .cell-code}\nraq_tib <- here::here(\"data/raq.csv\") |>\n  readr::read_csv()\n```\n\n::: {.cell-output .cell-output-stderr}\n\n```\nRows: 2571 Columns: 24\n── Column specification ────────────────────────────────────────────────────────\nDelimiter: \",\"\nchr  (1): id\ndbl (23): raq_01, raq_02, raq_03, raq_04, raq_05, raq_06, raq_07, raq_08, ra...\n\nℹ Use `spec()` to retrieve the full column specification for this data.\nℹ Specify the column types or set `show_col_types = FALSE` to quiet this message.\n```\n\n\n:::\n:::",
    "supporting": [],
    "filters": [
      "rmarkdown/pagebreak.lua"
    ],
    "includes": {},
    "engineDependencies": {},
    "preserve": {},
    "postProcess": true
  }
}